air_pollution/__init__.py
air_pollution/py.typed
air_pollution/luftmessnetz/__init__.py
air_pollution/luftmessnetz/_client.py
air_pollution/luftmessnetz/_models.py
air_pollution/luftmessnetz/_typing.py
air_pollution/luftmessnetz/aqi.py
air_pollution/scripts/__init__.py
air_pollution/scripts/downloader.py
air_pollution/uba/__init__.py
air_pollution/uba/_client.py
air_pollution/uba/_models.py
air_pollution/uba/_typing.py
air_pollution/uba/components/__init__.py
air_pollution/uba/components/_models.py
air_pollution/uba/measures/__init__.py
air_pollution/uba/measures/_models.py
air_pollution/uba/measures/_utils.py
air_pollution/uba/scopes/__init__.py
air_pollution/uba/scopes/_models.py
air_pollution-0.2.1.dist-info/licenses/LICENSE
air_pollution-0.2.1.dist-info/METADATA
air_pollution-0.2.1.dist-info/WHEEL
air_pollution-0.2.1.dist-info/entry_points.txt
air_pollution-0.2.1.dist-info/top_level.txt
air_pollution-0.2.1.dist-info/RECORD
